craft/__init__.py
craft/accumulator.py
craft/config.py
craft/data.py
craft/gradcache.py
craft/gradient_balancing.py
craft/hooks.py
craft/losses.py
craft/metrics.py
craft/trainers.py
contrastive_ft-0.4.3.dist-info/METADATA
contrastive_ft-0.4.3.dist-info/WHEEL
contrastive_ft-0.4.3.dist-info/RECORD
