Metadata-Version: 2.4
Name: contrastive-ft
Version: 0.4.3
Summary: CRAFT: Contrastive Representation Aware Fine-Tuning toolkit
Project-URL: Homepage, https://github.com/omarkamali/craft
Project-URL: Repository, https://github.com/omarkamali/craft
Project-URL: Issues, https://github.com/omarkamali/craft/issues
Author-email: "Omar Kamali (Omneity Labs)" <craft@omneitylabs.com>
Maintainer-email: Omneity Labs <craft@omneitylabs.com>
License: Apache-2.0
Requires-Python: >=3.9
Requires-Dist: numpy>=1.26
Requires-Dist: torch>=2.1
Provides-Extra: all
Requires-Dist: peft>=0.10; extra == 'all'
Requires-Dist: transformers>=4.43; extra == 'all'
Requires-Dist: trl>=0.9; extra == 'all'
Provides-Extra: hf
Requires-Dist: transformers>=4.43; extra == 'hf'
Provides-Extra: peft
Requires-Dist: peft>=0.10; extra == 'peft'
Requires-Dist: transformers>=4.43; extra == 'peft'
Provides-Extra: test
Requires-Dist: datasets>=2.0; extra == 'test'
Requires-Dist: pytest>=7; extra == 'test'
Requires-Dist: transformers>=4.43; extra == 'test'
Requires-Dist: trl>=0.9; extra == 'test'
Provides-Extra: trl
Requires-Dist: transformers>=4.43; extra == 'trl'
Requires-Dist: trl>=0.9; extra == 'trl'
